rgbpy/__init__.py
rgbpy/lcolor.py
rgbpy/tcolor.py
rgbpy-0.0.1.dist-info/LICENSE
rgbpy-0.0.1.dist-info/METADATA
rgbpy-0.0.1.dist-info/WHEEL
rgbpy-0.0.1.dist-info/top_level.txt
rgbpy-0.0.1.dist-info/RECORD
