Metadata-Version: 2.1
Name: rgbpy
Version: 0.0.1
Summary: RGBpy it is python text-style ✅ not python textile! 🤔 it actually print your text on terminal in different kind of colors, including logging.
Home-page: https://rgbpy.readthedocs.io
Download-URL: https://pypi.org/project/rgbpy
Author: Usman Musa
Author-email: usmanmusa1920@gmail.com
License: MIT
Project-URL: Documentation, https://rgbpy.readthedocs.io
Project-URL: Source, https://github.com/usmanmusa1920/rgbpy
Keywords: rgbpy
Platform: any
Classifier: Development Status :: 5 - Production/Stable
Classifier: Environment :: Other Environment
Classifier: Intended Audience :: Developers
Classifier: License :: OSI Approved :: MIT License
Classifier: Natural Language :: English
Classifier: Operating System :: OS Independent
Classifier: Programming Language :: Python
Classifier: Programming Language :: Python :: 3
Classifier: Programming Language :: Python :: 3.7
Classifier: Programming Language :: Python :: 3.8
Classifier: Programming Language :: Python :: 3.9
Classifier: Programming Language :: Python :: 3.10
Classifier: Topic :: Internet
Classifier: Topic :: Communications :: Email
Classifier: Topic :: Software Development :: Libraries :: Python Modules
Requires-Python: >=3.7
License-File: LICENSE
